cf_LRU_cache-0.0.1.dist-info/DESCRIPTION.rst
cf_LRU_cache-0.0.1.dist-info/METADATA
cf_LRU_cache-0.0.1.dist-info/RECORD
cf_LRU_cache-0.0.1.dist-info/WHEEL
cf_LRU_cache-0.0.1.dist-info/metadata.json
cf_LRU_cache-0.0.1.dist-info/top_level.txt
lru_cache/__init__.py
lru_cache/lru_cache.py
lru_cache/lru_cache_distributed.py
