Metadata-Version: 2.0
Name: cf-LRU-cache
Version: 0.0.1
Summary: LRU Cache Distributed
Home-page: https://github.com/carlos-ferras/code-challenge/cache
Author: Carlos Ferras
Author-email: c4rlos.ferra5@gmail.com
License: MIT
Platform: UNKNOWN
